all4scripts_zfullio/__init__.py
all4scripts_zfullio/allfoscript.py
all4scripts_zfullio-0.1.0.dist-info/LICENSE
all4scripts_zfullio-0.1.0.dist-info/METADATA
all4scripts_zfullio-0.1.0.dist-info/WHEEL
all4scripts_zfullio-0.1.0.dist-info/RECORD
