Metadata-Version: 2.1
Name: all4scripts-zfullio
Version: 0.1.0
Summary: Логгер и уведомления для скриптов
Author: viktor
Author-email: vi.dave@yandex.ru
Requires-Python: >=3.10,<3.11
Classifier: Programming Language :: Python :: 3
Classifier: Programming Language :: Python :: 3.10
Requires-Dist: loguru (>=0,<1)
Requires-Dist: notifiers (>=1.3.3,<2.0.0)
